vinci/__init__.py
vinci/core.py
vinci_sdk-0.1.3.dist-info/METADATA
vinci_sdk-0.1.3.dist-info/WHEEL
vinci_sdk-0.1.3.dist-info/RECORD
