Metadata-Version: 2.4
Name: vinci-sdk
Version: 0.1.3
Summary: The Leonardo Engine
Author-email: Davide <davide@example.com>
Requires-Python: >=3.8
